{
  "name": "projecty",
  "version": "0.1.0",
  "scripts": {
    "ng": "ng",
    "start": "ng serve --prod",
    "start-dev": "npm run copy-ds-files && ng serve",
    "build": "npm run copy-ds-files && ng build  --base-href /PoseidonNext/hss-modules/",
    "build-dev": "ng build --base-href /PoseidonNext/hss-modules/",
    "copy-ds-files": "copyfiles --up 2 ..\\..\\node_modules\\@kognifai\\design-system\\**\\* .",
    "update": "copy /Y package.publish.json dist\\package.json && copy /Y app.manifest.prod.json dist\\app.manifest.json && copy /Y src\\config.prod.json dist\\config.json",
    "test": "ng test --watch=false",
    "lint": "ng lint",
    "e2e": "ng e2e"
  },
  "author": "Kongsberg Digital",
  "publishConfig": {
    "directory": "dist"
  },
  "dependencies": {
    "@angular/animations": "^8.2.5",
    "@angular/cdk": "^9.2.4",
    "@angular/common": "~8.2.5",
    "@angular/compiler": "~8.2.5",
    "@angular/core": "~8.2.5",
    "@angular/forms": "~8.2.5",
    "@angular/http": "~7.2.15",
    "@angular/platform-browser": "~8.2.5",
    "@angular/platform-browser-dynamic": "~8.2.5",
    "@angular/router": "~8.2.5",
    "@kognifai/design-system": "^0.9.0-beta.5",
    "@kognifai/galore-client": "^4.0.0",
    "@kognifai/galore-ng-client": "^4.0.0",
    "@kognifai/poseidon-applocationsservice": "^5.0.0",
    "@kognifai/poseidon-authenticationservice": "^5.0.0",
    "@kognifai/poseidon-authredirect": "^5.0.0",
    "@kognifai/poseidon-breadcrumb-component": "^5.0.0",
    "@kognifai/poseidon-configurationinterface": "^5.0.0",
    "@kognifai/poseidon-cookieservice": "^5.0.0",
    "@kognifai/poseidon-datacontextservice": "^5.0.0",
    "@kognifai/poseidon-dropdown-directive": "^5.0.0",
    "@kognifai/poseidon-entitlements-query-service": "^5.0.0",
    "@kognifai/poseidon-header-component": "^5.0.0",
    "@kognifai/poseidon-message-service": "^5.0.0",
    "@kognifai/poseidon-navigationsidebar-component": "^5.0.0",
    "@kognifai/poseidon-ng-applocationsservice": "^5.0.0",
    "@kognifai/poseidon-ng-authenticationinterceptor": "^5.0.0",
    "@kognifai/poseidon-ng-authenticationservice": "^5.0.0",
    "@kognifai/poseidon-ng-configurationservice": "^5.0.0",
    "@kognifai/poseidon-ng-entitlements-query-service": "^5.0.0",
    "@kognifai/poseidon-ng-entitlementsguardservice": "^5.0.0",
    "@kognifai/poseidon-ng-global-settings": "^5.0.0",
    "@kognifai/poseidon-ng-initialize-service": "^5.0.0",
    "@kognifai/poseidon-ng-loading-component": "^5.0.0",
    "@kognifai/poseidon-ng-message-component": "^5.0.0",
    "@kognifai/poseidon-ng-navigation-subitems-service": "^5.0.0",
    "@kognifai/poseidon-ng-navigationservice": "^5.0.0",
    "@kognifai/poseidon-ng-page-not-found-component": "^5.0.0",
    "@kognifai/poseidon-ng-settings-menu": "^5.0.0",
    "@kognifai/poseidon-ng-settingsservice": "^5.0.0",
    "@kognifai/poseidon-ng-theming": "^5.0.0",
    "@kognifai/poseidon-ng-toolsmenuservice": "^5.0.0",
    "@kognifai/poseidon-ng-unauthorized-component": "^5.0.0",
    "@kognifai/poseidon-settingsservice": "^5.0.0",
    "@kognifai/poseidon-sidebar-visibilityservice": "^5.0.0",
    "@kognifai/poseidon-toolsmenu": "^5.0.0",
    "@types/leaflet": "^1.5.12",
    "@types/leaflet-rotatedmarker": "^0.2.1",
    "@types/leaflet.markercluster": "^1.4.2",
    "Leaflet.MultiOptionsPolyline": "github:hgoebl/Leaflet.MultiOptionsPolyline",
    "angular-google-charts": "^0.1.6",
    "angular-resize-event": "^1.2.1",
    "bootstrap": "4.3.1",
    "core-js": "^2.5.4",
    "d3": "^4.11.0",
    "file-saver": "^2.0.5",
    "google-charts": "^2.0.0",
    "google-libphonenumber": "3.2.15",
    "intl-tel-input": "17.0.8",
    "leaflet": "1.5.1",
    "leaflet-ant-path": "^1.3.0",
    "leaflet-fullscreen": "^1.0.2",
    "leaflet-rotatedmarker": "^0.2.0",
    "leaflet.markercluster": "^1.4.1",
    "lodash": "^4.17.4",
    "moment": "^2.29.1",
    "ngx-bootstrap": "5.6.2",
    "ngx-intl-tel-input": "2.5.4",
    "oidc-client": "1.5.2",
    "primeicons": "^2.0.0",
    "primeng": "8.0.0",
    "rxjs": "~6.5.3",
    "uuid": "^8.0.0",
    "zone.js": "^0.9.1"
  },
  "devDependencies": {
    "@angular-devkit/build-angular": "~0.803.3",
    "@angular/cli": "~8.3.3",
    "@angular/compiler-cli": "~8.2.5",
    "@angular/language-service": "~8.2.5",
    "@kognifai/poseidon-tslint": "^5.0.0",
    "@types/d3": "^4.10.1",
    "@types/file-saver": "^2.0.2",
    "@types/jasmine": "2.8.9",
    "@types/jasminewd2": "~2.0.3",
    "@types/node": "~8.9.4",
    "codelyzer": "^5.0.1",
    "copyfiles": "^2.0.0",
    "google-charts": "^2.0.0",
    "jasmine-core": "^3.4.0",
    "jasmine-spec-reporter": "~4.2.1",
    "karma": "^4.2.0",
    "karma-chrome-launcher": "^3.1.0",
    "karma-coverage-istanbul-reporter": "^2.1.0",
    "karma-jasmine": "^2.0.1",
    "karma-jasmine-html-reporter": "^1.4.2",
    "protractor": "^5.4.2",
    "ts-node": "~5.0.1",
    "tslint": "^5.19.0",
    "typescript": "~3.5.3"
  }
}
